{
    "Description": "Speaker name mappings to consolidate different spellings of the same person",
    "Instructions": "Add entries where the key is the source spelling (as it appears in the old database) and the value is the canonical/correct spelling you want to use",
    "Mappings": {
        "刘利": "刘利 Phillip Liu",
        "刘利/Philip Liu": "刘利 Phillip Liu",
        "刘利 Phillip": "刘利 Phillip Liu",
        "刘利/Phillip Liu": "刘利 Phillip Liu",
        "刘利弟兄 Bro Philip Liu": "刘利 Phillip Liu",
        "刘志雄": "刘志雄 Peter Liu",
        "卢銘华": "卢铭华 Alfred Lo",
        "卢铭华": "卢铭华 Alfred Lo",
        "卢铭华/Alfred Lo": "卢铭华 Alfred Lo",
        "卢铭华 Alfred Lu": "卢铭华 Alfred Lo",
        "史孟华": "史孟华 Michael Shi",
        "吴淼垚": "吴淼垚 Eric Wu",
        "夏绍军弟兄 Bro Fred": "夏绍军 Fred Xia",
        "孙国铎": "孙国铎 Godwin Sun",
        "孙国铎/Godwin sun": "孙国铎 Godwin Sun",
        "弟兄姐妹": "弟兄姊妹",
        "彭动平": "彭动平 Jonathan Pong",
        "彭动平 Jonathan Peng": "彭动平 Jonathan Pong",
        "彭广纯": "彭广纯 Ted Peng",
        "李爱成": "李爱成 Hudson Li",
        "李爱成弟兄 Bro Hudson Li": "李爱成 Hudson Li",
        "李爱诚": "李爱成 Hudson Li",
        "李和": "李禾 Barry Li",
        "李禾": "李禾 Barry Li",
        "李禾 Barry": "李禾 Barry Li",
        "李禾/Barry Li": "李禾 Barry Li",
        "Barry Li 李禾": "李禾 Barry Li",
        "江敏泉": "江敏泉 Eric Jiang",
        "江敏泉 Eric J": "江敏泉 Eric Jiang",
        "王伯熙": "王伯熙 Livingstone Wong",
        "王伯熙 Livingstone": "王伯熙 Livingstone Wong",
        "王伯熙/Livingstone Wong": "王伯熙 Livingstone Wong",
        "王伯熙 Wong": "王伯熙 Livingstone Wong",
        "程伟民": "程维民",
        "胡嘉冕Godwin": "胡嘉冕 Godwin Woo",
        "Godwin": "胡嘉冕 Godwin Woo",
        "David Woo": "胡沃江 David Woo",
        "胡沃江": "胡沃江 David Woo",
        "胡沃江DavidW": "胡沃江 David Woo",
        "胡沃江/David Woo": "胡沃江 David Woo",
        "袁飞": "袁飞 Michael Yuan",
        "袁飞/Michael Yuan": "袁飞 Michael Yuan",
        "许贤昌/YC": "许贤昌",
        "郑捷": "郑捷 Jie Zheng",
        "郑捷 Jie": "郑捷 Jie Zheng",
        "郭定强": "郭定强 Timothy Kwok",
        "郭定强/Timothy": "郭定强 Timothy Kwok",
        "郭定强/Timothy Kwoh": "郭定强 Timothy Kwok",
        "郭定强/Timothy Kwok": "郭定强 Timothy Kwok",
        "郭定强/Timothy Kwow": "郭定强 Timothy Kwok",
        "郭永楠": "郭永楠 Yongnan Guo",
        "赵国栋": "赵国栋 George Zhao",
        "黄汉先": "黄汉先 H S Wong"
    }
}